[
  {
    "nik": "3374010101010001",
    "nama": "Budi Santoso",
    "tempatLahir": "Semarang",
    "tanggalLahir": "1990-05-15",
    "jenisKelamin": "Laki-laki",
    "alamat": "Jl. Pleburan No. 123",
    "agama": "Islam",
    "statusPerkawinan": "Menikah",
    "pekerjaan": "Wiraswasta"
  },
  {
    "nik": "3374010101010002",
    "nama": "Siti Rahayu",
    "tempatLahir": "Semarang",
    "tanggalLahir": "1992-08-20",
    "jenisKelamin": "Perempuan",
    "alamat": "Jl. Pleburan No. 124",
    "agama": "Islam",
    "statusPerkawinan": "Menikah",
    "pekerjaan": "Ibu Rumah Tangga"
  },
  {
    "nik": "3374010101010003",
    "nama": "Joko Widodo",
    "tempatLahir": "Semarang",
    "tanggalLahir": "1985-11-10",
    "jenisKelamin": "Laki-laki",
    "alamat": "Jl. Pleburan No. 125",
    "agama": "Islam",
    "statusPerkawinan": "Menikah",
    "pekerjaan": "Pegawai Negeri"
  }
]
